cpskin/__init__.py
cpskin/core/__init__.py
cpskin/core/adapter.py
cpskin/core/configure.zcml
cpskin/core/events.py
cpskin/core/extender.py
cpskin/core/indexer.py
cpskin/core/interfaces.py
cpskin/core/monkey.zcml
cpskin/core/monkeypatches.py
cpskin/core/overrides.zcml
cpskin/core/permissions.py
cpskin/core/permissions.zcml
cpskin/core/privacy.py
cpskin/core/privacy.zcml
cpskin/core/profiles.zcml
cpskin/core/registryreader.py
cpskin/core/setuphandlers.py
cpskin/core/testing.py
cpskin/core/testing.zcml
cpskin/core/upgradehandlers.py
cpskin/core/utils.py
cpskin/core/vocabulary.py
cpskin/core/behaviors/__init__.py
cpskin/core/behaviors/booking.py
cpskin/core/behaviors/configure.zcml
cpskin/core/behaviors/directory.py
cpskin/core/behaviors/directorycontact.py
cpskin/core/behaviors/eventview.py
cpskin/core/behaviors/indexview.py
cpskin/core/behaviors/metadata.py
cpskin/core/behaviors/organization.py
cpskin/core/browser/__init__.py
cpskin/core/browser/banner.py
cpskin/core/browser/collective_contact_view.py
cpskin/core/browser/common.py
cpskin/core/browser/configure.zcml
cpskin/core/browser/contactdetails.py
cpskin/core/browser/contentviews.pt
cpskin/core/browser/controlpanel.py
cpskin/core/browser/document.py
cpskin/core/browser/event_listing.py
cpskin/core/browser/file.py
cpskin/core/browser/folder.py
cpskin/core/browser/folderish.py
cpskin/core/browser/folderview.py
cpskin/core/browser/form.py
cpskin/core/browser/interfaces.py
cpskin/core/browser/layout.py
cpskin/core/browser/media.py
cpskin/core/browser/navigation.py
cpskin/core/browser/organization.py
cpskin/core/browser/pages.py
cpskin/core/browser/privacy.py
cpskin/core/browser/register.py
cpskin/core/browser/search.py
cpskin/core/browser/sendtomanager.py
cpskin/core/browser/sunburstview.py
cpskin/core/browser/utils.py
cpskin/core/browser/widget.py
cpskin/core/browser/overrides/plone.app.contenttypes.browser.templates.listing_summary.pt
cpskin.core-0.14.11.dist-info/DESCRIPTION.rst
cpskin.core-0.14.11.dist-info/METADATA
cpskin.core-0.14.11.dist-info/RECORD
cpskin.core-0.14.11.dist-info/WHEEL
cpskin.core-0.14.11.dist-info/metadata.json
cpskin.core-0.14.11.dist-info/top_level.txt
