Metadata-Version: 2.0
Name: cpskin.core
Version: 0.14.11
Summary: Core package for cpskin
Home-page: https://github.com/imio/cpskin.core
Author: IMIO
Author-email: support@imio.be
License: gpl
Platform: UNKNOWN
Classifier: Environment :: Web Environment
Classifier: Programming Language :: Python
Classifier: Programming Language :: Python :: 2.7
Classifier: Framework :: Plone
Classifier: Framework :: Plone :: 4.2
Classifier: Framework :: Plone :: 4.3
Provides-Extra: test
Requires-Dist: setuptools
Requires-Dist: z3c.unconfigure
Requires-Dist: cpskin.locales
Requires-Dist: cpskin.citizen
Requires-Dist: cpskin.minisite
Requires-Dist: cpskin.menu
Requires-Dist: plone.api
Requires-Dist: plone.app.contenttypes
Requires-Dist: Plone
Requires-Dist: archetypes.schemaextender
Requires-Dist: imio.ckeditortemplates
Requires-Dist: collective.directory
Requires-Dist: collective.monkeypatcher
Requires-Dist: imio.media
Requires-Dist: collective.plonetruegallery
Requires-Dist: collective.geo.faceted
Requires-Dist: plone.behavior
Requires-Dist: collective.sticky
Requires-Dist: collective.quickupload
Requires-Dist: wildcard.foldercontents
Requires-Dist: eea.facetednavigation
Requires-Dist: collective.iconifieddocumentactions
Requires-Dist: collective.z3cform.keywordwidget
Requires-Dist: httpagentparser
Requires-Dist: collective.contact.core
Requires-Dist: collective.folderishtypes
Requires-Dist: collective.taxonomy
Requires-Dist: collective.navigationtoggle
Requires-Dist: imio.dashboard
Requires-Dist: collective.jsonify
Requires-Dist: phonenumbers
Requires-Dist: collective.contact.facetednav
Requires-Dist: collective.dexteritytextindexer
Requires-Dist: plone.app.imagecropping
Requires-Dist: plone.app.multilingual
Requires-Dist: plone.app.event
Requires-Dist: z3c.jbot
Requires-Dist: sc.social.like
Requires-Dist: collective.js.fancybox
Requires-Dist: imio.gdpr
Requires-Dist: collective.printrss
Requires-Dist: collective.recaptcha
Requires-Dist: collective.sendinblue (<2.0)
Requires-Dist: collective.lesscss
Requires-Dist: collective.anysurfer
Requires-Dist: collective.privacy
Requires-Dist: iaweb.privacy
Provides-Extra: test
Requires-Dist: plone.app.robotframework; extra == 'test'
Requires-Dist: plone.app.multilingual; extra == 'test'
Requires-Dist: Products.contentmigration; extra == 'test'
Requires-Dist: ipdb; extra == 'test'
Requires-Dist: cpskin.workflow; extra == 'test'
